adjsoned/__init__.py
adjsoned/_text_processing.py
adjsoned/file_json_properties.py
adjsoned/json_properties.py
adjsoned-0.0.3.dist-info/METADATA
adjsoned-0.0.3.dist-info/WHEEL
adjsoned-0.0.3.dist-info/top_level.txt
adjsoned-0.0.3.dist-info/RECORD
