Metadata-Version: 2.1
Name: adjsoned
Version: 0.0.3
Summary: Loads required properties/config from a json file to a Python runtime object
Home-page: https://adjsoned.readthedocs.io/
Author: Dan Demidov
Author-email: demidob.dev@gmail.com
License: MIT
Platform: UNKNOWN
Classifier: Intended Audience :: Developers
Classifier: License :: OSI Approved :: MIT License
Classifier: Programming Language :: Python
Classifier: Programming Language :: Python :: 3
Classifier: Programming Language :: Python :: 3.7
Classifier: Programming Language :: Python :: 3.8
Classifier: Programming Language :: Python :: 3.9
Classifier: Programming Language :: Python :: 3.10
Classifier: Programming Language :: Python :: 3.11
Classifier: Operating System :: OS Independent
